[
  {
    "line": 1,
    "elements": [
      {
        "start_timestamp": "2021-11-18T19:07:03.481Z",
        "before": [
          {
            "result": {
              "duration": 4223000,
              "status": "passed"
            },
            "match": {
              "location": "stepdefinitions.Hooks.setUp()"
            }
          }
        ],
        "line": 3,
        "name": "TC19 DB Util ile Concort Hotel Database Read Test",
        "description": "",
        "id": "us1013-kullanici-db-util-ile-concort-hotel-database-ini-test-eder;tc19-db-util-ile-concort-hotel-database-read-test",
        "after": [
          {
            "result": {
              "duration": 6315221000,
              "status": "passed"
            },
            "match": {
              "location": "stepdefinitions.Hooks.tearDown(io.cucumber.java.Scenario)"
            }
          }
        ],
        "type": "scenario",
        "keyword": "Scenario",
        "steps": [
          {
            "result": {
              "status": "undefined"
            },
            "line": 5,
            "name": "kullanici DBUtill ile CHQA database\u0027ine baglanir",
            "match": {},
            "keyword": "Given "
          },
          {
            "result": {
              "duration": 176000,
              "status": "skipped"
            },
            "line": 6,
            "name": "kullanici DBUtill ile \"tHOTELROOM\" tablosundaki \"Price\" verilerini alir",
            "match": {},
            "keyword": "And "
          },
          {
            "result": {
              "duration": 342000,
              "status": "skipped"
            },
            "line": 7,
            "name": "kullanici DBUtill ile \"Price\" sutunundaki 5. fiyatin 400 oldugunu test eder",
            "match": {},
            "keyword": "And "
          }
        ],
        "tags": [
          {
            "name": "@dbutill"
          }
        ]
      }
    ],
    "name": "US1013 Kullanici DB Util ile concort Hotel database\u0027ini test eder",
    "description": "",
    "id": "us1013-kullanici-db-util-ile-concort-hotel-database-ini-test-eder",
    "keyword": "Feature",
    "uri": "file:src/test/resources/features/US1013_DbUtilTests.feature",
    "tags": []
  }
]